<root>
	<styles>
	<include src="s2r://panorama/styles/dotastyles.vcss_c" />
	<include src="s2r://panorama/styles/ready_up_players.vcss_c" />
	</styles>

	<DOTAReadyUpPlayers>

		<Panel id="PlayerReadyUp" class="TopBottomFlow StatusTextContainer">
			<Panel class="LeftRightFlow">
				<Panel class="PlayerList">
					<DOTAReadyUpPlayerSlot id="PlayerSlot_0" />
					<DOTAReadyUpPlayerSlot id="PlayerSlot_1" />
					<DOTAReadyUpPlayerSlot id="PlayerSlot_2" />
					<DOTAReadyUpPlayerSlot id="PlayerSlot_3" />
					<DOTAReadyUpPlayerSlot id="PlayerSlot_4" />
				</Panel>
				<Panel class="ListSpacer"/>
				<Panel class="PlayerList">
					<DOTAReadyUpPlayerSlot id="PlayerSlot_5" />
					<DOTAReadyUpPlayerSlot id="PlayerSlot_6" />
					<DOTAReadyUpPlayerSlot id="PlayerSlot_7" />
					<DOTAReadyUpPlayerSlot id="PlayerSlot_8" />
					<DOTAReadyUpPlayerSlot id="PlayerSlot_9" />
				</Panel>
			</Panel>
			<Label id="AcceptedCount" text="#dota_ready_up_num_accepted" />
		</Panel>

		<Panel id="ReturningToQueue">
			<Label text="#returning_top_of_queue" />
		</Panel>

		<Panel id="ReturningToLobby">
			<Label text="#returning_to_lobby" />
		</Panel>

	</DOTAReadyUpPlayers>
</root>
